{"sentences":[{"index":0,"tokens":[{"index":1,"word":"From","originalText":"From","characterOffsetBegin":0,"characterOffsetEnd":4,"pos":"IN","before":"","after":""},{"index":2,"word":":","originalText":":","characterOffsetBegin":4,"characterOffsetEnd":5,"pos":":","before":"","after":" "},{"index":3,"word":"Marc","originalText":"Marc","characterOffsetBegin":6,"characterOffsetEnd":10,"pos":"NNP","before":" ","after":" "},{"index":4,"word":"VanHeyningen","originalText":"VanHeyningen","characterOffsetBegin":11,"characterOffsetEnd":23,"pos":"NNP","before":" ","after":" "},{"index":5,"word":"<mvanheyn@cs.indiana.edu>","originalText":"<mvanheyn@cs.indiana.edu>","characterOffsetBegin":24,"characterOffsetEnd":49,"pos":"NNP","before":" ","after":""},{"index":6,"word":"Subject","originalText":"Subject","characterOffsetBegin":49,"characterOffsetEnd":56,"pos":"NNP","before":"","after":""},{"index":7,"word":":","originalText":":","characterOffsetBegin":56,"characterOffsetEnd":57,"pos":":","before":"","after":" "},{"index":8,"word":"How","originalText":"How","characterOffsetBegin":58,"characterOffsetEnd":61,"pos":"WRB","before":" ","after":" "},{"index":9,"word":"does","originalText":"does","characterOffsetBegin":62,"characterOffsetEnd":66,"pos":"VBZ","before":" ","after":" "},{"index":10,"word":"it","originalText":"it","characterOffsetBegin":67,"characterOffsetEnd":69,"pos":"PRP","before":" ","after":" "},{"index":11,"word":"really","originalText":"really","characterOffsetBegin":70,"characterOffsetEnd":76,"pos":"RB","before":" ","after":" "},{"index":12,"word":"work","originalText":"work","characterOffsetBegin":77,"characterOffsetEnd":81,"pos":"VB","before":" ","after":""},{"index":13,"word":"?","originalText":"?","characterOffsetBegin":81,"characterOffsetEnd":82,"pos":".","before":"","after":" "}]},{"index":1,"tokens":[{"index":1,"word":"-LRB-","originalText":"(","characterOffsetBegin":83,"characterOffsetEnd":84,"pos":"-LRB-","before":" ","after":""},{"index":2,"word":"was","originalText":"was","characterOffsetBegin":84,"characterOffsetEnd":87,"pos":"VBD","before":"","after":" "},{"index":3,"word":"Re","originalText":"Re","characterOffsetBegin":88,"characterOffsetEnd":90,"pos":"NNP","before":" ","after":""},{"index":4,"word":":","originalText":":","characterOffsetBegin":90,"characterOffsetEnd":91,"pos":":","before":"","after":" "},{"index":5,"word":"text","originalText":"text","characterOffsetBegin":92,"characterOffsetEnd":96,"pos":"NN","before":" ","after":" "},{"index":6,"word":"of","originalText":"of","characterOffsetBegin":97,"characterOffsetEnd":99,"pos":"IN","before":" ","after":" "},{"index":7,"word":"White","originalText":"White","characterOffsetBegin":100,"characterOffsetEnd":105,"pos":"NNP","before":" ","after":" "},{"index":8,"word":"House","originalText":"House","characterOffsetBegin":106,"characterOffsetEnd":111,"pos":"NNP","before":" ","after":" "},{"index":9,"word":"announcement","originalText":"announcement","characterOffsetBegin":112,"characterOffsetEnd":124,"pos":"NN","before":" ","after":" "},{"index":10,"word":"and","originalText":"and","characterOffsetBegin":125,"characterOffsetEnd":128,"pos":"CC","before":" ","after":" "},{"index":11,"word":"Q&A","originalText":"Q&A","characterOffsetBegin":129,"characterOffsetEnd":132,"pos":"NN","before":" ","after":""},{"index":12,"word":"s","originalText":"s","characterOffsetBegin":132,"characterOffsetEnd":133,"pos":"NNS","before":"","after":" "},{"index":13,"word":"on","originalText":"on","characterOffsetBegin":134,"characterOffsetEnd":136,"pos":"IN","before":" ","after":" "},{"index":14,"word":"clipper","originalText":"clipper","characterOffsetBegin":137,"characterOffsetEnd":144,"pos":"NN","before":" ","after":" "},{"index":15,"word":"chip","originalText":"chip","characterOffsetBegin":145,"characterOffsetEnd":149,"pos":"NN","before":" ","after":" "},{"index":16,"word":"encryption","originalText":"encryption","characterOffsetBegin":150,"characterOffsetEnd":160,"pos":"NN","before":" ","after":""},{"index":17,"word":"-RRB-","originalText":")","characterOffsetBegin":160,"characterOffsetEnd":161,"pos":"-RRB-","before":"","after":""},{"index":18,"word":"Organization","originalText":"Organization","characterOffsetBegin":161,"characterOffsetEnd":173,"pos":"NNP","before":"","after":""},{"index":19,"word":":","originalText":":","characterOffsetBegin":173,"characterOffsetEnd":174,"pos":":","before":"","after":" "},{"index":20,"word":"Computer","originalText":"Computer","characterOffsetBegin":175,"characterOffsetEnd":183,"pos":"NNP","before":" ","after":" "},{"index":21,"word":"Science","originalText":"Science","characterOffsetBegin":184,"characterOffsetEnd":191,"pos":"NNP","before":" ","after":" "},{"index":22,"word":"Dept","originalText":"Dept","characterOffsetBegin":192,"characterOffsetEnd":196,"pos":"NNP","before":" ","after":""},{"index":23,"word":",","originalText":",","characterOffsetBegin":196,"characterOffsetEnd":197,"pos":",","before":"","after":" "},{"index":24,"word":"Indiana","originalText":"Indiana","characterOffsetBegin":198,"characterOffsetEnd":205,"pos":"NNP","before":" ","after":" "},{"index":25,"word":"UniversityDistribution","originalText":"UniversityDistribution","characterOffsetBegin":206,"characterOffsetEnd":228,"pos":"NNP","before":" ","after":""},{"index":26,"word":":","originalText":":","characterOffsetBegin":228,"characterOffsetEnd":229,"pos":":","before":"","after":" "},{"index":27,"word":"naLines","originalText":"naLines","characterOffsetBegin":230,"characterOffsetEnd":237,"pos":"NNS","before":" ","after":""},{"index":28,"word":":","originalText":":","characterOffsetBegin":237,"characterOffsetEnd":238,"pos":":","before":"","after":" "},{"index":29,"word":"57This","originalText":"57This","characterOffsetBegin":239,"characterOffsetEnd":245,"pos":"JJ","before":" ","after":" "},{"index":30,"word":"announcement","originalText":"announcement","characterOffsetBegin":246,"characterOffsetEnd":258,"pos":"NN","before":" ","after":" "},{"index":31,"word":"is","originalText":"is","characterOffsetBegin":259,"characterOffsetEnd":261,"pos":"VBZ","before":" ","after":" "},{"index":32,"word":"somewhat","originalText":"somewhat","characterOffsetBegin":262,"characterOffsetEnd":270,"pos":"RB","before":" ","after":" "},{"index":33,"word":"disconcerting","originalText":"disconcerting","characterOffsetBegin":271,"characterOffsetEnd":284,"pos":"JJ","before":" ","after":""},{"index":34,"word":";","originalText":";","characterOffsetBegin":284,"characterOffsetEnd":285,"pos":":","before":"","after":" "},{"index":35,"word":"it","originalText":"it","characterOffsetBegin":286,"characterOffsetEnd":288,"pos":"PRP","before":" ","after":" "},{"index":36,"word":"does","originalText":"does","characterOffsetBegin":289,"characterOffsetEnd":293,"pos":"VBZ","before":" ","after":""},{"index":37,"word":"n't","originalText":"n't","characterOffsetBegin":293,"characterOffsetEnd":296,"pos":"RB","before":"","after":" "},{"index":38,"word":"do","originalText":"do","characterOffsetBegin":297,"characterOffsetEnd":299,"pos":"VB","before":" ","after":" "},{"index":39,"word":"anythingevil","originalText":"anythingevil","characterOffsetBegin":300,"characterOffsetEnd":312,"pos":"NN","before":" ","after":" "},{"index":40,"word":"in","originalText":"in","characterOffsetBegin":313,"characterOffsetEnd":315,"pos":"IN","before":" ","after":" "},{"index":41,"word":"and","originalText":"and","characterOffsetBegin":316,"characterOffsetEnd":319,"pos":"CC","before":" ","after":" "},{"index":42,"word":"of","originalText":"of","characterOffsetBegin":320,"characterOffsetEnd":322,"pos":"IN","before":" ","after":" "},{"index":43,"word":"itself","originalText":"itself","characterOffsetBegin":323,"characterOffsetEnd":329,"pos":"PRP","before":" ","after":""},{"index":44,"word":",","originalText":",","characterOffsetBegin":329,"characterOffsetEnd":330,"pos":",","before":"","after":" "},{"index":45,"word":"but","originalText":"but","characterOffsetBegin":331,"characterOffsetEnd":334,"pos":"CC","before":" ","after":" "},{"index":46,"word":"bodes","originalText":"bodes","characterOffsetBegin":335,"characterOffsetEnd":340,"pos":"VBZ","before":" ","after":" "},{"index":47,"word":"badly","originalText":"badly","characterOffsetBegin":341,"characterOffsetEnd":346,"pos":"RB","before":" ","after":" "},{"index":48,"word":"for","originalText":"for","characterOffsetBegin":347,"characterOffsetEnd":350,"pos":"IN","before":" ","after":" "},{"index":49,"word":"the","originalText":"the","characterOffsetBegin":351,"characterOffsetEnd":354,"pos":"DT","before":" ","after":" "},{"index":50,"word":"future","originalText":"future","characterOffsetBegin":355,"characterOffsetEnd":361,"pos":"NN","before":" ","after":" "},{"index":51,"word":"of","originalText":"of","characterOffsetBegin":362,"characterOffsetEnd":364,"pos":"IN","before":" ","after":" "},{"index":52,"word":"openalgorithms","originalText":"openalgorithms","characterOffsetBegin":365,"characterOffsetEnd":379,"pos":"NNS","before":" ","after":" "},{"index":53,"word":"and","originalText":"and","characterOffsetBegin":380,"characterOffsetEnd":383,"pos":"CC","before":" ","after":" "},{"index":54,"word":"standards","originalText":"standards","characterOffsetBegin":384,"characterOffsetEnd":393,"pos":"NNS","before":" ","after":" "},{"index":55,"word":"in","originalText":"in","characterOffsetBegin":394,"characterOffsetEnd":396,"pos":"IN","before":" ","after":" "},{"index":56,"word":"information","originalText":"information","characterOffsetBegin":397,"characterOffsetEnd":408,"pos":"NN","before":" ","after":" "},{"index":57,"word":"security","originalText":"security","characterOffsetBegin":409,"characterOffsetEnd":417,"pos":"NN","before":" ","after":""},{"index":58,"word":".","originalText":".","characterOffsetBegin":417,"characterOffsetEnd":418,"pos":".","before":"","after":"  "}]},{"index":2,"tokens":[{"index":1,"word":"I","originalText":"I","characterOffsetBegin":420,"characterOffsetEnd":421,"pos":"PRP","before":"  ","after":" "},{"index":2,"word":"wo","originalText":"wo","characterOffsetBegin":422,"characterOffsetEnd":424,"pos":"MD","before":" ","after":""},{"index":3,"word":"n't","originalText":"n't","characterOffsetBegin":424,"characterOffsetEnd":427,"pos":"RB","before":"","after":" "},{"index":4,"word":"startpanicking","originalText":"startpanicking","characterOffsetBegin":428,"characterOffsetEnd":442,"pos":"VBG","before":" ","after":" "},{"index":5,"word":"until/unless","originalText":"until/unless","characterOffsetBegin":443,"characterOffsetEnd":455,"pos":"JJ","before":" ","after":" "},{"index":6,"word":"DES","originalText":"DES","characterOffsetBegin":456,"characterOffsetEnd":459,"pos":"NNP","before":" ","after":" "},{"index":7,"word":"or","originalText":"or","characterOffsetBegin":460,"characterOffsetEnd":462,"pos":"CC","before":" ","after":" "},{"index":8,"word":"RSA","originalText":"RSA","characterOffsetBegin":463,"characterOffsetEnd":466,"pos":"NNP","before":" ","after":" "},{"index":9,"word":"or","originalText":"or","characterOffsetBegin":467,"characterOffsetEnd":469,"pos":"CC","before":" ","after":" "},{"index":10,"word":"stuff","originalText":"stuff","characterOffsetBegin":470,"characterOffsetEnd":475,"pos":"NN","before":" ","after":" "},{"index":11,"word":"like","originalText":"like","characterOffsetBegin":476,"characterOffsetEnd":480,"pos":"IN","before":" ","after":" "},{"index":12,"word":"that","originalText":"that","characterOffsetBegin":481,"characterOffsetEnd":485,"pos":"DT","before":" ","after":" "},{"index":13,"word":"is","originalText":"is","characterOffsetBegin":486,"characterOffsetEnd":488,"pos":"VBZ","before":" ","after":" "},{"index":14,"word":"prohibited","originalText":"prohibited","characterOffsetBegin":489,"characterOffsetEnd":499,"pos":"VBN","before":" ","after":""},{"index":15,"word":",","originalText":",","characterOffsetBegin":499,"characterOffsetEnd":500,"pos":",","before":"","after":" "},{"index":16,"word":"butI","originalText":"butI","characterOffsetBegin":501,"characterOffsetEnd":505,"pos":"NNP","before":" ","after":""},{"index":17,"word":"'m","originalText":"'m","characterOffsetBegin":505,"characterOffsetEnd":507,"pos":"VBP","before":"","after":" "},{"index":18,"word":"a","originalText":"a","characterOffsetBegin":508,"characterOffsetEnd":509,"pos":"DT","before":" ","after":" "},{"index":19,"word":"little","originalText":"little","characterOffsetBegin":510,"characterOffsetEnd":516,"pos":"JJ","before":" ","after":" "},{"index":20,"word":"anxious","originalText":"anxious","characterOffsetBegin":517,"characterOffsetEnd":524,"pos":"JJ","before":" ","after":""},{"index":21,"word":".","originalText":".","characterOffsetBegin":524,"characterOffsetEnd":525,"pos":".","before":"","after":"  "}]},{"index":3,"tokens":[{"index":1,"word":"-LRB-","originalText":"(","characterOffsetBegin":527,"characterOffsetEnd":528,"pos":"-LRB-","before":"  ","after":""},{"index":2,"word":"No","originalText":"No","characterOffsetBegin":528,"characterOffsetEnd":530,"pos":"DT","before":"","after":" "},{"index":3,"word":"doubt","originalText":"doubt","characterOffsetBegin":531,"characterOffsetEnd":536,"pos":"NN","before":" ","after":" "},{"index":4,"word":"it","originalText":"it","characterOffsetBegin":537,"characterOffsetEnd":539,"pos":"PRP","before":" ","after":" "},{"index":5,"word":"wo","originalText":"wo","characterOffsetBegin":540,"characterOffsetEnd":542,"pos":"MD","before":" ","after":""},{"index":6,"word":"n't","originalText":"n't","characterOffsetBegin":542,"characterOffsetEnd":545,"pos":"RB","before":"","after":" "},{"index":7,"word":"be","originalText":"be","characterOffsetBegin":546,"characterOffsetEnd":548,"pos":"VB","before":" ","after":" "},{"index":8,"word":"long","originalText":"long","characterOffsetBegin":549,"characterOffsetEnd":553,"pos":"JJ","before":" ","after":" "},{"index":9,"word":"before","originalText":"before","characterOffsetBegin":554,"characterOffsetEnd":560,"pos":"IN","before":" ","after":" "},{"index":10,"word":"someone","originalText":"someone","characterOffsetBegin":561,"characterOffsetEnd":568,"pos":"NN","before":" ","after":" "},{"index":11,"word":"postsexplaining","originalText":"postsexplaining","characterOffsetBegin":569,"characterOffsetEnd":584,"pos":"VBG","before":" ","after":" "},{"index":12,"word":"how","originalText":"how","characterOffsetBegin":585,"characterOffsetEnd":588,"pos":"WRB","before":" ","after":" "},{"index":13,"word":"this","originalText":"this","characterOffsetBegin":589,"characterOffsetEnd":593,"pos":"DT","before":" ","after":" "},{"index":14,"word":"just","originalText":"just","characterOffsetBegin":594,"characterOffsetEnd":598,"pos":"RB","before":" ","after":" "},{"index":15,"word":"a","originalText":"a","characterOffsetBegin":599,"characterOffsetEnd":600,"pos":"DT","before":" ","after":" "},{"index":16,"word":"small","originalText":"small","characterOffsetBegin":601,"characterOffsetEnd":606,"pos":"JJ","before":" ","after":" "},{"index":17,"word":"part","originalText":"part","characterOffsetBegin":607,"characterOffsetEnd":611,"pos":"NN","before":" ","after":" "},{"index":18,"word":"of","originalText":"of","characterOffsetBegin":612,"characterOffsetEnd":614,"pos":"IN","before":" ","after":" "},{"index":19,"word":"some","originalText":"some","characterOffsetBegin":615,"characterOffsetEnd":619,"pos":"DT","before":" ","after":" "},{"index":20,"word":"far-ranging","originalText":"far-ranging","characterOffsetBegin":620,"characterOffsetEnd":631,"pos":"JJ","before":" ","after":" "},{"index":21,"word":"andlong-lived","originalText":"andlong-lived","characterOffsetBegin":632,"characterOffsetEnd":645,"pos":"JJ","before":" ","after":" "},{"index":22,"word":"NSA-PKP-IRS-FBI-CIA-HandgunControlInc-Clinton","originalText":"NSA-PKP-IRS-FBI-CIA-HandgunControlInc-Clinton","characterOffsetBegin":646,"characterOffsetEnd":691,"pos":"NN","before":" ","after":" "},{"index":23,"word":"conspiracy","originalText":"conspiracy","characterOffsetBegin":692,"characterOffsetEnd":702,"pos":"NN","before":" ","after":" "},{"index":24,"word":"tosubvert","originalText":"tosubvert","characterOffsetBegin":703,"characterOffsetEnd":712,"pos":"NN","before":" ","after":" "},{"index":25,"word":"freedom","originalText":"freedom","characterOffsetBegin":713,"characterOffsetEnd":720,"pos":"NN","before":" ","after":""},{"index":26,"word":",","originalText":",","characterOffsetBegin":720,"characterOffsetEnd":721,"pos":",","before":"","after":" "},{"index":27,"word":"democracy","originalText":"democracy","characterOffsetBegin":722,"characterOffsetEnd":731,"pos":"NN","before":" ","after":""},{"index":28,"word":",","originalText":",","characterOffsetBegin":731,"characterOffsetEnd":732,"pos":",","before":"","after":" "},{"index":29,"word":"and","originalText":"and","characterOffsetBegin":733,"characterOffsetEnd":736,"pos":"CC","before":" ","after":" "},{"index":30,"word":"mathematics","originalText":"mathematics","characterOffsetBegin":737,"characterOffsetEnd":748,"pos":"NN","before":" ","after":""},{"index":31,"word":".","originalText":".","characterOffsetBegin":748,"characterOffsetEnd":749,"pos":".","before":"","after":""},{"index":32,"word":"-RRB-","originalText":")","characterOffsetBegin":749,"characterOffsetEnd":750,"pos":"-RRB-","before":"","after":"  "}]},{"index":4,"tokens":[{"index":1,"word":"My","originalText":"My","characterOffsetBegin":752,"characterOffsetEnd":754,"pos":"PRP$","before":"  ","after":" "},{"index":2,"word":"feeling","originalText":"feeling","characterOffsetBegin":755,"characterOffsetEnd":762,"pos":"NN","before":" ","after":" "},{"index":3,"word":"is","originalText":"is","characterOffsetBegin":763,"characterOffsetEnd":765,"pos":"VBZ","before":" ","after":" "},{"index":4,"word":"that","originalText":"that","characterOffsetBegin":766,"characterOffsetEnd":770,"pos":"IN","before":" ","after":" "},{"index":5,"word":"theadministration","originalText":"theadministration","characterOffsetBegin":771,"characterOffsetEnd":788,"pos":"NN","before":" ","after":" "},{"index":6,"word":"probably","originalText":"probably","characterOffsetBegin":789,"characterOffsetEnd":797,"pos":"RB","before":" ","after":" "},{"index":7,"word":"is","originalText":"is","characterOffsetBegin":798,"characterOffsetEnd":800,"pos":"VBZ","before":" ","after":""},{"index":8,"word":"n't","originalText":"n't","characterOffsetBegin":800,"characterOffsetEnd":803,"pos":"RB","before":"","after":" "},{"index":9,"word":"that","originalText":"that","characterOffsetBegin":804,"characterOffsetEnd":808,"pos":"IN","before":" ","after":" "},{"index":10,"word":"worried","originalText":"worried","characterOffsetBegin":809,"characterOffsetEnd":816,"pos":"JJ","before":" ","after":" "},{"index":11,"word":"about","originalText":"about","characterOffsetBegin":817,"characterOffsetEnd":822,"pos":"IN","before":" ","after":" "},{"index":12,"word":"things","originalText":"things","characterOffsetBegin":823,"characterOffsetEnd":829,"pos":"NNS","before":" ","after":" "},{"index":13,"word":"like","originalText":"like","characterOffsetBegin":830,"characterOffsetEnd":834,"pos":"IN","before":" ","after":" "},{"index":14,"word":"DES","originalText":"DES","characterOffsetBegin":835,"characterOffsetEnd":838,"pos":"NNP","before":" ","after":" "},{"index":15,"word":"andRSA","originalText":"andRSA","characterOffsetBegin":839,"characterOffsetEnd":845,"pos":"NNP","before":" ","after":" "},{"index":16,"word":"and","originalText":"and","characterOffsetBegin":846,"characterOffsetEnd":849,"pos":"CC","before":" ","after":" "},{"index":17,"word":"PGP","originalText":"PGP","characterOffsetBegin":850,"characterOffsetEnd":853,"pos":"NNP","before":" ","after":" "},{"index":18,"word":"and","originalText":"and","characterOffsetBegin":854,"characterOffsetEnd":857,"pos":"CC","before":" ","after":" "},{"index":19,"word":"RIPEM","originalText":"RIPEM","characterOffsetBegin":858,"characterOffsetEnd":863,"pos":"NNP","before":" ","after":""},{"index":20,"word":",","originalText":",","characterOffsetBegin":863,"characterOffsetEnd":864,"pos":",","before":"","after":" "},{"index":21,"word":"since","originalText":"since","characterOffsetBegin":865,"characterOffsetEnd":870,"pos":"IN","before":" ","after":" "},{"index":22,"word":"they","originalText":"they","characterOffsetBegin":871,"characterOffsetEnd":875,"pos":"PRP","before":" ","after":""},{"index":23,"word":"'ll","originalText":"'ll","characterOffsetBegin":875,"characterOffsetEnd":878,"pos":"MD","before":"","after":" "},{"index":24,"word":"never","originalText":"never","characterOffsetBegin":879,"characterOffsetEnd":884,"pos":"RB","before":" ","after":" "},{"index":25,"word":"be","originalText":"be","characterOffsetBegin":885,"characterOffsetEnd":887,"pos":"VB","before":" ","after":" "},{"index":26,"word":"used","originalText":"used","characterOffsetBegin":888,"characterOffsetEnd":892,"pos":"VBN","before":" ","after":" "},{"index":27,"word":"by","originalText":"by","characterOffsetBegin":893,"characterOffsetEnd":895,"pos":"IN","before":" ","after":" "},{"index":28,"word":"a","originalText":"a","characterOffsetBegin":896,"characterOffsetEnd":897,"pos":"DT","before":" ","after":" "},{"index":29,"word":"group","originalText":"group","characterOffsetBegin":898,"characterOffsetEnd":903,"pos":"NN","before":" ","after":" "},{"index":30,"word":"muchwider","originalText":"muchwider","characterOffsetBegin":904,"characterOffsetEnd":913,"pos":"NN","before":" ","after":" "},{"index":31,"word":"than","originalText":"than","characterOffsetBegin":914,"characterOffsetEnd":918,"pos":"IN","before":" ","after":" "},{"index":32,"word":"us","originalText":"us","characterOffsetBegin":919,"characterOffsetEnd":921,"pos":"PRP","before":" ","after":" "},{"index":33,"word":"computer","originalText":"computer","characterOffsetBegin":922,"characterOffsetEnd":930,"pos":"NN","before":" ","after":" "},{"index":34,"word":"geeks.The","originalText":"geeks.The","characterOffsetBegin":931,"characterOffsetEnd":940,"pos":"NN","before":" ","after":" "},{"index":35,"word":"fact","originalText":"fact","characterOffsetBegin":941,"characterOffsetEnd":945,"pos":"NN","before":" ","after":" "},{"index":36,"word":"that","originalText":"that","characterOffsetBegin":946,"characterOffsetEnd":950,"pos":"IN","before":" ","after":" "},{"index":37,"word":"this","originalText":"this","characterOffsetBegin":951,"characterOffsetEnd":955,"pos":"DT","before":" ","after":" "},{"index":38,"word":"just","originalText":"just","characterOffsetBegin":956,"characterOffsetEnd":960,"pos":"RB","before":" ","after":" "},{"index":39,"word":"came","originalText":"came","characterOffsetBegin":961,"characterOffsetEnd":965,"pos":"VBD","before":" ","after":" "},{"index":40,"word":"out","originalText":"out","characterOffsetBegin":966,"characterOffsetEnd":969,"pos":"RP","before":" ","after":" "},{"index":41,"word":"now","originalText":"now","characterOffsetBegin":970,"characterOffsetEnd":973,"pos":"RB","before":" ","after":" "},{"index":42,"word":"suggests","originalText":"suggests","characterOffsetBegin":974,"characterOffsetEnd":982,"pos":"VBZ","before":" ","after":" "},{"index":43,"word":"one","originalText":"one","characterOffsetBegin":983,"characterOffsetEnd":986,"pos":"CD","before":" ","after":" "},{"index":44,"word":"of","originalText":"of","characterOffsetBegin":987,"characterOffsetEnd":989,"pos":"IN","before":" ","after":" "},{"index":45,"word":"two","originalText":"two","characterOffsetBegin":990,"characterOffsetEnd":993,"pos":"CD","before":" ","after":" "},{"index":46,"word":"things","originalText":"things","characterOffsetBegin":994,"characterOffsetEnd":1000,"pos":"NNS","before":" ","after":""},{"index":47,"word":":1","originalText":":1","characterOffsetBegin":1000,"characterOffsetEnd":1002,"pos":"CD","before":"","after":""},{"index":48,"word":".","originalText":".","characterOffsetBegin":1002,"characterOffsetEnd":1003,"pos":".","before":"","after":"  "}]},{"index":5,"tokens":[{"index":1,"word":"The","originalText":"The","characterOffsetBegin":1005,"characterOffsetEnd":1008,"pos":"DT","before":"  ","after":" "},{"index":2,"word":"NSA","originalText":"NSA","characterOffsetBegin":1009,"characterOffsetEnd":1012,"pos":"NNP","before":" ","after":" "},{"index":3,"word":"has","originalText":"has","characterOffsetBegin":1013,"characterOffsetEnd":1016,"pos":"VBZ","before":" ","after":" "},{"index":4,"word":"been","originalText":"been","characterOffsetBegin":1017,"characterOffsetEnd":1021,"pos":"VBN","before":" ","after":" "},{"index":5,"word":"working","originalText":"working","characterOffsetBegin":1022,"characterOffsetEnd":1029,"pos":"VBG","before":" ","after":" "},{"index":6,"word":"on","originalText":"on","characterOffsetBegin":1030,"characterOffsetEnd":1032,"pos":"IN","before":" ","after":" "},{"index":7,"word":"this","originalText":"this","characterOffsetBegin":1033,"characterOffsetEnd":1037,"pos":"DT","before":" ","after":" "},{"index":8,"word":"for","originalText":"for","characterOffsetBegin":1038,"characterOffsetEnd":1041,"pos":"IN","before":" ","after":" "},{"index":9,"word":"a","originalText":"a","characterOffsetBegin":1042,"characterOffsetEnd":1043,"pos":"DT","before":" ","after":" "},{"index":10,"word":"long","originalText":"long","characterOffsetBegin":1044,"characterOffsetEnd":1048,"pos":"JJ","before":" ","after":" "},{"index":11,"word":"time","originalText":"time","characterOffsetBegin":1049,"characterOffsetEnd":1053,"pos":"NN","before":" ","after":""},{"index":12,"word":",","originalText":",","characterOffsetBegin":1053,"characterOffsetEnd":1054,"pos":",","before":"","after":" "},{"index":13,"word":"and","originalText":"and","characterOffsetBegin":1055,"characterOffsetEnd":1058,"pos":"CC","before":" ","after":" "},{"index":14,"word":"it","originalText":"it","characterOffsetBegin":1059,"characterOffsetEnd":1061,"pos":"PRP","before":" ","after":" "},{"index":15,"word":"only","originalText":"only","characterOffsetBegin":1062,"characterOffsetEnd":1066,"pos":"RB","before":" ","after":" "},{"index":16,"word":"just","originalText":"just","characterOffsetBegin":1067,"characterOffsetEnd":1071,"pos":"RB","before":" ","after":"    "},{"index":17,"word":"now","originalText":"now","characterOffsetBegin":1075,"characterOffsetEnd":1078,"pos":"RB","before":"    ","after":" "},{"index":18,"word":"happened","originalText":"happened","characterOffsetBegin":1079,"characterOffsetEnd":1087,"pos":"VBN","before":" ","after":" "},{"index":19,"word":"to","originalText":"to","characterOffsetBegin":1088,"characterOffsetEnd":1090,"pos":"TO","before":" ","after":" "},{"index":20,"word":"be","originalText":"be","characterOffsetBegin":1091,"characterOffsetEnd":1093,"pos":"VB","before":" ","after":" "},{"index":21,"word":"``","originalText":"``","characterOffsetBegin":1094,"characterOffsetEnd":1096,"pos":"``","before":" ","after":""},{"index":22,"word":"ready","originalText":"ready","characterOffsetBegin":1096,"characterOffsetEnd":1101,"pos":"JJ","before":"","after":""},{"index":23,"word":"''","originalText":"''","characterOffsetBegin":1101,"characterOffsetEnd":1103,"pos":"''","before":"","after":" "},{"index":24,"word":"to","originalText":"to","characterOffsetBegin":1104,"characterOffsetEnd":1106,"pos":"TO","before":" ","after":" "},{"index":25,"word":"release","originalText":"release","characterOffsetBegin":1107,"characterOffsetEnd":1114,"pos":"VB","before":" ","after":" "},{"index":26,"word":"to","originalText":"to","characterOffsetBegin":1115,"characterOffsetEnd":1117,"pos":"TO","before":" ","after":" "},{"index":27,"word":"the","originalText":"the","characterOffsetBegin":1118,"characterOffsetEnd":1121,"pos":"DT","before":" ","after":" "},{"index":28,"word":"world","originalText":"world","characterOffsetBegin":1122,"characterOffsetEnd":1127,"pos":"NN","before":" ","after":" "},{"index":29,"word":"at","originalText":"at","characterOffsetBegin":1128,"characterOffsetEnd":1130,"pos":"IN","before":" ","after":" "},{"index":30,"word":"this","originalText":"this","characterOffsetBegin":1131,"characterOffsetEnd":1135,"pos":"DT","before":" ","after":" "},{"index":31,"word":"time","originalText":"time","characterOffsetBegin":1136,"characterOffsetEnd":1140,"pos":"NN","before":" ","after":""},{"index":32,"word":".2","originalText":".2","characterOffsetBegin":1140,"characterOffsetEnd":1142,"pos":"NN","before":"","after":""},{"index":33,"word":".","originalText":".","characterOffsetBegin":1142,"characterOffsetEnd":1143,"pos":".","before":"","after":"  "}]},{"index":6,"tokens":[{"index":1,"word":"The","originalText":"The","characterOffsetBegin":1145,"characterOffsetEnd":1148,"pos":"DT","before":"  ","after":" "},{"index":2,"word":"NSA","originalText":"NSA","characterOffsetBegin":1149,"characterOffsetEnd":1152,"pos":"NNP","before":" ","after":" "},{"index":3,"word":"has","originalText":"has","characterOffsetBegin":1153,"characterOffsetEnd":1156,"pos":"VBZ","before":" ","after":" "},{"index":4,"word":"been","originalText":"been","characterOffsetBegin":1157,"characterOffsetEnd":1161,"pos":"VBN","before":" ","after":" "},{"index":5,"word":"working","originalText":"working","characterOffsetBegin":1162,"characterOffsetEnd":1169,"pos":"VBG","before":" ","after":" "},{"index":6,"word":"on","originalText":"on","characterOffsetBegin":1170,"characterOffsetEnd":1172,"pos":"IN","before":" ","after":" "},{"index":7,"word":"this","originalText":"this","characterOffsetBegin":1173,"characterOffsetEnd":1177,"pos":"DT","before":" ","after":" "},{"index":8,"word":"for","originalText":"for","characterOffsetBegin":1178,"characterOffsetEnd":1181,"pos":"IN","before":" ","after":" "},{"index":9,"word":"a","originalText":"a","characterOffsetBegin":1182,"characterOffsetEnd":1183,"pos":"DT","before":" ","after":" "},{"index":10,"word":"long","originalText":"long","characterOffsetBegin":1184,"characterOffsetEnd":1188,"pos":"JJ","before":" ","after":" "},{"index":11,"word":"time","originalText":"time","characterOffsetBegin":1189,"characterOffsetEnd":1193,"pos":"NN","before":" ","after":""},{"index":12,"word":",","originalText":",","characterOffsetBegin":1193,"characterOffsetEnd":1194,"pos":",","before":"","after":" "},{"index":13,"word":"but","originalText":"but","characterOffsetBegin":1195,"characterOffsetEnd":1198,"pos":"CC","before":" ","after":" "},{"index":14,"word":"was","originalText":"was","characterOffsetBegin":1199,"characterOffsetEnd":1202,"pos":"VBD","before":" ","after":""},{"index":15,"word":"n't","originalText":"n't","characterOffsetBegin":1202,"characterOffsetEnd":1205,"pos":"RB","before":"","after":" "},{"index":16,"word":"able","originalText":"able","characterOffsetBegin":1206,"characterOffsetEnd":1210,"pos":"JJ","before":" ","after":"    "},{"index":17,"word":"to","originalText":"to","characterOffsetBegin":1214,"characterOffsetEnd":1216,"pos":"TO","before":"    ","after":" "},{"index":18,"word":"get","originalText":"get","characterOffsetBegin":1217,"characterOffsetEnd":1220,"pos":"VB","before":" ","after":" "},{"index":19,"word":"the","originalText":"the","characterOffsetBegin":1221,"characterOffsetEnd":1224,"pos":"DT","before":" ","after":" "},{"index":20,"word":"Bush","originalText":"Bush","characterOffsetBegin":1225,"characterOffsetEnd":1229,"pos":"NNP","before":" ","after":" "},{"index":21,"word":"administration","originalText":"administration","characterOffsetBegin":1230,"characterOffsetEnd":1244,"pos":"NN","before":" ","after":" "},{"index":22,"word":"to","originalText":"to","characterOffsetBegin":1245,"characterOffsetEnd":1247,"pos":"TO","before":" ","after":" "},{"index":23,"word":"go","originalText":"go","characterOffsetBegin":1248,"characterOffsetEnd":1250,"pos":"VB","before":" ","after":" "},{"index":24,"word":"along","originalText":"along","characterOffsetBegin":1251,"characterOffsetEnd":1256,"pos":"RP","before":" ","after":" "},{"index":25,"word":"with","originalText":"with","characterOffsetBegin":1257,"characterOffsetEnd":1261,"pos":"IN","before":" ","after":" "},{"index":26,"word":"this","originalText":"this","characterOffsetBegin":1262,"characterOffsetEnd":1266,"pos":"DT","before":" ","after":" "},{"index":27,"word":"plan","originalText":"plan","characterOffsetBegin":1267,"characterOffsetEnd":1271,"pos":"NN","before":" ","after":""},{"index":28,"word":".","originalText":".","characterOffsetBegin":1271,"characterOffsetEnd":1272,"pos":".","before":"","after":"  "}]},{"index":7,"tokens":[{"index":1,"word":"-LRB-","originalText":"(","characterOffsetBegin":1274,"characterOffsetEnd":1275,"pos":"-LRB-","before":"  ","after":""},{"index":2,"word":"I","originalText":"I","characterOffsetBegin":1275,"characterOffsetEnd":1276,"pos":"PRP","before":"","after":"    "},{"index":3,"word":"find","originalText":"find","characterOffsetBegin":1280,"characterOffsetEnd":1284,"pos":"VBP","before":"    ","after":" "},{"index":4,"word":"it","originalText":"it","characterOffsetBegin":1285,"characterOffsetEnd":1287,"pos":"PRP","before":" ","after":" "},{"index":5,"word":"unlikely","originalText":"unlikely","characterOffsetBegin":1288,"characterOffsetEnd":1296,"pos":"JJ","before":" ","after":" "},{"index":6,"word":"that","originalText":"that","characterOffsetBegin":1297,"characterOffsetEnd":1301,"pos":"IN","before":" ","after":" "},{"index":7,"word":"this","originalText":"this","characterOffsetBegin":1302,"characterOffsetEnd":1306,"pos":"DT","before":" ","after":" "},{"index":8,"word":"would","originalText":"would","characterOffsetBegin":1307,"characterOffsetEnd":1312,"pos":"MD","before":" ","after":" "},{"index":9,"word":"have","originalText":"have","characterOffsetBegin":1313,"characterOffsetEnd":1317,"pos":"VB","before":" ","after":" "},{"index":10,"word":"been","originalText":"been","characterOffsetBegin":1318,"characterOffsetEnd":1322,"pos":"VBN","before":" ","after":" "},{"index":11,"word":"because","originalText":"because","characterOffsetBegin":1323,"characterOffsetEnd":1330,"pos":"IN","before":" ","after":" "},{"index":12,"word":"of","originalText":"of","characterOffsetBegin":1331,"characterOffsetEnd":1333,"pos":"IN","before":" ","after":" "},{"index":13,"word":"a","originalText":"a","characterOffsetBegin":1334,"characterOffsetEnd":1335,"pos":"DT","before":" ","after":" "},{"index":14,"word":"sympathy","originalText":"sympathy","characterOffsetBegin":1336,"characterOffsetEnd":1344,"pos":"NN","before":" ","after":"    "},{"index":15,"word":"for","originalText":"for","characterOffsetBegin":1348,"characterOffsetEnd":1351,"pos":"IN","before":"    ","after":" "},{"index":16,"word":"the","originalText":"the","characterOffsetBegin":1352,"characterOffsetEnd":1355,"pos":"DT","before":" ","after":" "},{"index":17,"word":"unescrowed","originalText":"unescrowed","characterOffsetBegin":1356,"characterOffsetEnd":1366,"pos":"JJ","before":" ","after":" "},{"index":18,"word":"use","originalText":"use","characterOffsetBegin":1367,"characterOffsetEnd":1370,"pos":"NN","before":" ","after":" "},{"index":19,"word":"of","originalText":"of","characterOffsetBegin":1371,"characterOffsetEnd":1373,"pos":"IN","before":" ","after":" "},{"index":20,"word":"cryptography","originalText":"cryptography","characterOffsetBegin":1374,"characterOffsetEnd":1386,"pos":"NN","before":" ","after":""},{"index":21,"word":";","originalText":";","characterOffsetBegin":1386,"characterOffsetEnd":1387,"pos":":","before":"","after":" "},{"index":22,"word":"more","originalText":"more","characterOffsetBegin":1388,"characterOffsetEnd":1392,"pos":"RBR","before":" ","after":" "},{"index":23,"word":"likely","originalText":"likely","characterOffsetBegin":1393,"characterOffsetEnd":1399,"pos":"JJ","before":" ","after":" "},{"index":24,"word":"the","originalText":"the","characterOffsetBegin":1400,"characterOffsetEnd":1403,"pos":"DT","before":" ","after":"    "},{"index":25,"word":"administration","originalText":"administration","characterOffsetBegin":1407,"characterOffsetEnd":1421,"pos":"NN","before":"    ","after":" "},{"index":26,"word":"felt","originalText":"felt","characterOffsetBegin":1422,"characterOffsetEnd":1426,"pos":"VBD","before":" ","after":" "},{"index":27,"word":"that","originalText":"that","characterOffsetBegin":1427,"characterOffsetEnd":1431,"pos":"IN","before":" ","after":" "},{"index":28,"word":"even","originalText":"even","characterOffsetBegin":1432,"characterOffsetEnd":1436,"pos":"RB","before":" ","after":" "},{"index":29,"word":"escrowed","originalText":"escrowed","characterOffsetBegin":1437,"characterOffsetEnd":1445,"pos":"VBN","before":" ","after":""},{"index":30,"word":",","originalText":",","characterOffsetBegin":1445,"characterOffsetEnd":1446,"pos":",","before":"","after":" "},{"index":31,"word":"secret-algorithm","originalText":"secret-algorithm","characterOffsetBegin":1447,"characterOffsetEnd":1463,"pos":"NN","before":" ","after":" "},{"index":32,"word":"and","originalText":"and","characterOffsetBegin":1464,"characterOffsetEnd":1467,"pos":"CC","before":" ","after":""},{"index":33,"word":",","originalText":",","characterOffsetBegin":1467,"characterOffsetEnd":1468,"pos":",","before":"","after":" "},{"index":34,"word":"for","originalText":"for","characterOffsetBegin":1469,"characterOffsetEnd":1472,"pos":"IN","before":" ","after":"    "},{"index":35,"word":"all","originalText":"all","characterOffsetBegin":1476,"characterOffsetEnd":1479,"pos":"DT","before":"    ","after":" "},{"index":36,"word":"we","originalText":"we","characterOffsetBegin":1480,"characterOffsetEnd":1482,"pos":"PRP","before":" ","after":" "},{"index":37,"word":"know","originalText":"know","characterOffsetBegin":1483,"characterOffsetEnd":1487,"pos":"VBP","before":" ","after":""},{"index":38,"word":",","originalText":",","characterOffsetBegin":1487,"characterOffsetEnd":1488,"pos":",","before":"","after":" "},{"index":39,"word":"trivially","originalText":"trivially","characterOffsetBegin":1489,"characterOffsetEnd":1498,"pos":"RB","before":" ","after":" "},{"index":40,"word":"breakable","originalText":"breakable","characterOffsetBegin":1499,"characterOffsetEnd":1508,"pos":"JJ","before":" ","after":" "},{"index":41,"word":"cryptography","originalText":"cryptography","characterOffsetBegin":1509,"characterOffsetEnd":1521,"pos":"NN","before":" ","after":" "},{"index":42,"word":"should","originalText":"should","characterOffsetBegin":1522,"characterOffsetEnd":1528,"pos":"MD","before":" ","after":" "},{"index":43,"word":"not","originalText":"not","characterOffsetBegin":1529,"characterOffsetEnd":1532,"pos":"RB","before":" ","after":" "},{"index":44,"word":"be","originalText":"be","characterOffsetBegin":1533,"characterOffsetEnd":1535,"pos":"VB","before":" ","after":" "},{"index":45,"word":"made","originalText":"made","characterOffsetBegin":1536,"characterOffsetEnd":1540,"pos":"VBN","before":" ","after":"    "},{"index":46,"word":"widely","originalText":"widely","characterOffsetBegin":1544,"characterOffsetEnd":1550,"pos":"RB","before":"    ","after":" "},{"index":47,"word":"available","originalText":"available","characterOffsetBegin":1551,"characterOffsetEnd":1560,"pos":"JJ","before":" ","after":""},{"index":48,"word":".","originalText":".","characterOffsetBegin":1560,"characterOffsetEnd":1561,"pos":".","before":"","after":""},{"index":49,"word":"-RRB-","originalText":")","characterOffsetBegin":1561,"characterOffsetEnd":1562,"pos":"-RRB-","before":"","after":""}]},{"index":8,"tokens":[{"index":1,"word":"Thus","originalText":"Thus","characterOffsetBegin":1562,"characterOffsetEnd":1566,"pos":"RB","before":"","after":" "},{"index":2,"word":"said","originalText":"said","characterOffsetBegin":1567,"characterOffsetEnd":1571,"pos":"VBD","before":" ","after":" "},{"index":3,"word":"clipper@csrc.ncsl.nist.gov","originalText":"clipper@csrc.ncsl.nist.gov","characterOffsetBegin":1572,"characterOffsetEnd":1598,"pos":"NN","before":" ","after":" "},{"index":4,"word":"-LRB-","originalText":"(","characterOffsetBegin":1599,"characterOffsetEnd":1600,"pos":"-LRB-","before":" ","after":""},{"index":5,"word":"Clipper","originalText":"Clipper","characterOffsetBegin":1600,"characterOffsetEnd":1607,"pos":"NNP","before":"","after":" "},{"index":6,"word":"Chip","originalText":"Chip","characterOffsetBegin":1608,"characterOffsetEnd":1612,"pos":"NNP","before":" ","after":" "},{"index":7,"word":"Announcement","originalText":"Announcement","characterOffsetBegin":1613,"characterOffsetEnd":1625,"pos":"NN","before":" ","after":""},{"index":8,"word":"-RRB-","originalText":")","characterOffsetBegin":1625,"characterOffsetEnd":1626,"pos":"-RRB-","before":"","after":""},{"index":9,"word":":","originalText":":","characterOffsetBegin":1626,"characterOffsetEnd":1627,"pos":":","before":"","after":""},{"index":10,"word":">","originalText":">","characterOffsetBegin":1627,"characterOffsetEnd":1628,"pos":"JJR","before":"","after":""},{"index":11,"word":"This","originalText":"This","characterOffsetBegin":1628,"characterOffsetEnd":1632,"pos":"DT","before":"","after":" "},{"index":12,"word":"new","originalText":"new","characterOffsetBegin":1633,"characterOffsetEnd":1636,"pos":"JJ","before":" ","after":" "},{"index":13,"word":"technology","originalText":"technology","characterOffsetBegin":1637,"characterOffsetEnd":1647,"pos":"NN","before":" ","after":" "},{"index":14,"word":"will","originalText":"will","characterOffsetBegin":1648,"characterOffsetEnd":1652,"pos":"MD","before":" ","after":" "},{"index":15,"word":"help","originalText":"help","characterOffsetBegin":1653,"characterOffsetEnd":1657,"pos":"VB","before":" ","after":" "},{"index":16,"word":"companies","originalText":"companies","characterOffsetBegin":1658,"characterOffsetEnd":1667,"pos":"NNS","before":" ","after":" "},{"index":17,"word":"protect","originalText":"protect","characterOffsetBegin":1668,"characterOffsetEnd":1675,"pos":"VBP","before":" ","after":" "},{"index":18,"word":"proprietary","originalText":"proprietary","characterOffsetBegin":1676,"characterOffsetEnd":1687,"pos":"JJ","before":" ","after":""},{"index":19,"word":">","originalText":">","characterOffsetBegin":1687,"characterOffsetEnd":1688,"pos":"JJR","before":"","after":""},{"index":20,"word":"information","originalText":"information","characterOffsetBegin":1688,"characterOffsetEnd":1699,"pos":"NN","before":"","after":""},{"index":21,"word":",","originalText":",","characterOffsetBegin":1699,"characterOffsetEnd":1700,"pos":",","before":"","after":" "},{"index":22,"word":"protect","originalText":"protect","characterOffsetBegin":1701,"characterOffsetEnd":1708,"pos":"VBP","before":" ","after":" "},{"index":23,"word":"the","originalText":"the","characterOffsetBegin":1709,"characterOffsetEnd":1712,"pos":"DT","before":" ","after":" "},{"index":24,"word":"privacy","originalText":"privacy","characterOffsetBegin":1713,"characterOffsetEnd":1720,"pos":"NN","before":" ","after":" "},{"index":25,"word":"of","originalText":"of","characterOffsetBegin":1721,"characterOffsetEnd":1723,"pos":"IN","before":" ","after":" "},{"index":26,"word":"personal","originalText":"personal","characterOffsetBegin":1724,"characterOffsetEnd":1732,"pos":"JJ","before":" ","after":" "},{"index":27,"word":"phone","originalText":"phone","characterOffsetBegin":1733,"characterOffsetEnd":1738,"pos":"NN","before":" ","after":" "},{"index":28,"word":"conversations","originalText":"conversations","characterOffsetBegin":1739,"characterOffsetEnd":1752,"pos":"NNS","before":" ","after":""},{"index":29,"word":">","originalText":">","characterOffsetBegin":1752,"characterOffsetEnd":1753,"pos":"JJR","before":"","after":""},{"index":30,"word":"and","originalText":"and","characterOffsetBegin":1753,"characterOffsetEnd":1756,"pos":"CC","before":"","after":" "},{"index":31,"word":"prevent","originalText":"prevent","characterOffsetBegin":1757,"characterOffsetEnd":1764,"pos":"VB","before":" ","after":" "},{"index":32,"word":"unauthorized","originalText":"unauthorized","characterOffsetBegin":1765,"characterOffsetEnd":1777,"pos":"JJ","before":" ","after":" "},{"index":33,"word":"release","originalText":"release","characterOffsetBegin":1778,"characterOffsetEnd":1785,"pos":"NN","before":" ","after":" "},{"index":34,"word":"of","originalText":"of","characterOffsetBegin":1786,"characterOffsetEnd":1788,"pos":"IN","before":" ","after":" "},{"index":35,"word":"data","originalText":"data","characterOffsetBegin":1789,"characterOffsetEnd":1793,"pos":"NNS","before":" ","after":" "},{"index":36,"word":"transmitted","originalText":"transmitted","characterOffsetBegin":1794,"characterOffsetEnd":1805,"pos":"VBN","before":" ","after":""},{"index":37,"word":">","originalText":">","characterOffsetBegin":1805,"characterOffsetEnd":1806,"pos":"JJR","before":"","after":""},{"index":38,"word":"electronically","originalText":"electronically","characterOffsetBegin":1806,"characterOffsetEnd":1820,"pos":"RB","before":"","after":""},{"index":39,"word":".","originalText":".","characterOffsetBegin":1820,"characterOffsetEnd":1821,"pos":".","before":"","after":"  "}]},{"index":9,"tokens":[{"index":1,"word":"At","originalText":"At","characterOffsetBegin":1823,"characterOffsetEnd":1825,"pos":"IN","before":"  ","after":" "},{"index":2,"word":"the","originalText":"the","characterOffsetBegin":1826,"characterOffsetEnd":1829,"pos":"DT","before":" ","after":" "},{"index":3,"word":"same","originalText":"same","characterOffsetBegin":1830,"characterOffsetEnd":1834,"pos":"JJ","before":" ","after":" "},{"index":4,"word":"time","originalText":"time","characterOffsetBegin":1835,"characterOffsetEnd":1839,"pos":"NN","before":" ","after":" "},{"index":5,"word":"this","originalText":"this","characterOffsetBegin":1840,"characterOffsetEnd":1844,"pos":"DT","before":" ","after":" "},{"index":6,"word":"technology","originalText":"technology","characterOffsetBegin":1845,"characterOffsetEnd":1855,"pos":"NN","before":" ","after":" "},{"index":7,"word":"preserves","originalText":"preserves","characterOffsetBegin":1856,"characterOffsetEnd":1865,"pos":"VBZ","before":" ","after":" "},{"index":8,"word":"the","originalText":"the","characterOffsetBegin":1866,"characterOffsetEnd":1869,"pos":"DT","before":" ","after":""},{"index":9,"word":">","originalText":">","characterOffsetBegin":1869,"characterOffsetEnd":1870,"pos":"JJR","before":"","after":""},{"index":10,"word":"ability","originalText":"ability","characterOffsetBegin":1870,"characterOffsetEnd":1877,"pos":"NN","before":"","after":" "},{"index":11,"word":"of","originalText":"of","characterOffsetBegin":1878,"characterOffsetEnd":1880,"pos":"IN","before":" ","after":" "},{"index":12,"word":"federal","originalText":"federal","characterOffsetBegin":1881,"characterOffsetEnd":1888,"pos":"JJ","before":" ","after":""},{"index":13,"word":",","originalText":",","characterOffsetBegin":1888,"characterOffsetEnd":1889,"pos":",","before":"","after":" "},{"index":14,"word":"state","originalText":"state","characterOffsetBegin":1890,"characterOffsetEnd":1895,"pos":"NN","before":" ","after":" "},{"index":15,"word":"and","originalText":"and","characterOffsetBegin":1896,"characterOffsetEnd":1899,"pos":"CC","before":" ","after":" "},{"index":16,"word":"local","originalText":"local","characterOffsetBegin":1900,"characterOffsetEnd":1905,"pos":"JJ","before":" ","after":" "},{"index":17,"word":"law","originalText":"law","characterOffsetBegin":1906,"characterOffsetEnd":1909,"pos":"NN","before":" ","after":" "},{"index":18,"word":"enforcement","originalText":"enforcement","characterOffsetBegin":1910,"characterOffsetEnd":1921,"pos":"NN","before":" ","after":" "},{"index":19,"word":"agencies","originalText":"agencies","characterOffsetBegin":1922,"characterOffsetEnd":1930,"pos":"NNS","before":" ","after":" "},{"index":20,"word":"to","originalText":"to","characterOffsetBegin":1931,"characterOffsetEnd":1933,"pos":"TO","before":" ","after":""},{"index":21,"word":">","originalText":">","characterOffsetBegin":1933,"characterOffsetEnd":1934,"pos":"JJR","before":"","after":""},{"index":22,"word":"intercept","originalText":"intercept","characterOffsetBegin":1934,"characterOffsetEnd":1943,"pos":"VB","before":"","after":" "},{"index":23,"word":"lawfully","originalText":"lawfully","characterOffsetBegin":1944,"characterOffsetEnd":1952,"pos":"RB","before":" ","after":" "},{"index":24,"word":"the","originalText":"the","characterOffsetBegin":1953,"characterOffsetEnd":1956,"pos":"DT","before":" ","after":" "},{"index":25,"word":"phone","originalText":"phone","characterOffsetBegin":1957,"characterOffsetEnd":1962,"pos":"NN","before":" ","after":" "},{"index":26,"word":"conversations","originalText":"conversations","characterOffsetBegin":1963,"characterOffsetEnd":1976,"pos":"NNS","before":" ","after":" "},{"index":27,"word":"of","originalText":"of","characterOffsetBegin":1977,"characterOffsetEnd":1979,"pos":"IN","before":" ","after":" "},{"index":28,"word":"criminals","originalText":"criminals","characterOffsetBegin":1980,"characterOffsetEnd":1989,"pos":"NNS","before":" ","after":""},{"index":29,"word":".","originalText":".","characterOffsetBegin":1989,"characterOffsetEnd":1990,"pos":".","before":"","after":" "}]},{"index":10,"tokens":[{"index":1,"word":"The","originalText":"The","characterOffsetBegin":1991,"characterOffsetEnd":1994,"pos":"DT","before":" ","after":" "},{"index":2,"word":"majority","originalText":"majority","characterOffsetBegin":1995,"characterOffsetEnd":2003,"pos":"NN","before":" ","after":" "},{"index":3,"word":"of","originalText":"of","characterOffsetBegin":2004,"characterOffsetEnd":2006,"pos":"IN","before":" ","after":" "},{"index":4,"word":"the","originalText":"the","characterOffsetBegin":2007,"characterOffsetEnd":2010,"pos":"DT","before":" ","after":" "},{"index":5,"word":"discussion","originalText":"discussion","characterOffsetBegin":2011,"characterOffsetEnd":2021,"pos":"NN","before":" ","after":" "},{"index":6,"word":"involving","originalText":"involving","characterOffsetBegin":2022,"characterOffsetEnd":2031,"pos":"VBG","before":" ","after":" "},{"index":7,"word":"this","originalText":"this","characterOffsetBegin":2032,"characterOffsetEnd":2036,"pos":"DT","before":" ","after":" "},{"index":8,"word":"``","originalText":"\"","characterOffsetBegin":2037,"characterOffsetEnd":2038,"pos":"``","before":" ","after":""},{"index":9,"word":"Clipper","originalText":"Clipper","characterOffsetBegin":2038,"characterOffsetEnd":2045,"pos":"NNP","before":"","after":" "},{"index":10,"word":"Chip","originalText":"Chip","characterOffsetBegin":2046,"characterOffsetEnd":2050,"pos":"NNP","before":" ","after":""},{"index":11,"word":"''","originalText":"\"","characterOffsetBegin":2050,"characterOffsetEnd":2051,"pos":"''","before":"","after":" "},{"index":12,"word":"seems","originalText":"seems","characterOffsetBegin":2052,"characterOffsetEnd":2057,"pos":"VBZ","before":" ","after":" "},{"index":13,"word":"topertain","originalText":"topertain","characterOffsetBegin":2058,"characterOffsetEnd":2067,"pos":"NN","before":" ","after":" "},{"index":14,"word":"to","originalText":"to","characterOffsetBegin":2068,"characterOffsetEnd":2070,"pos":"TO","before":" ","after":" "},{"index":15,"word":"the","originalText":"the","characterOffsetBegin":2071,"characterOffsetEnd":2074,"pos":"DT","before":" ","after":" "},{"index":16,"word":"encryption","originalText":"encryption","characterOffsetBegin":2075,"characterOffsetEnd":2085,"pos":"NN","before":" ","after":" "},{"index":17,"word":"of","originalText":"of","characterOffsetBegin":2086,"characterOffsetEnd":2088,"pos":"IN","before":" ","after":" "},{"index":18,"word":"telephone","originalText":"telephone","characterOffsetBegin":2089,"characterOffsetEnd":2098,"pos":"NN","before":" ","after":" "},{"index":19,"word":"conversations","originalText":"conversations","characterOffsetBegin":2099,"characterOffsetEnd":2112,"pos":"NNS","before":" ","after":""},{"index":20,"word":".","originalText":".","characterOffsetBegin":2112,"characterOffsetEnd":2113,"pos":".","before":"","after":"  "}]},{"index":11,"tokens":[{"index":1,"word":"Does","originalText":"Does","characterOffsetBegin":2115,"characterOffsetEnd":2119,"pos":"VBZ","before":"  ","after":" "},{"index":2,"word":"anyoneknow","originalText":"anyoneknow","characterOffsetBegin":2120,"characterOffsetEnd":2130,"pos":"NN","before":" ","after":" "},{"index":3,"word":"if","originalText":"if","characterOffsetBegin":2131,"characterOffsetEnd":2133,"pos":"IN","before":" ","after":" "},{"index":4,"word":"that","originalText":"that","characterOffsetBegin":2134,"characterOffsetEnd":2138,"pos":"DT","before":" ","after":" "},{"index":5,"word":"means","originalText":"means","characterOffsetBegin":2139,"characterOffsetEnd":2144,"pos":"VBZ","before":" ","after":" "},{"index":6,"word":"this","originalText":"this","characterOffsetBegin":2145,"characterOffsetEnd":2149,"pos":"DT","before":" ","after":" "},{"index":7,"word":"chip","originalText":"chip","characterOffsetBegin":2150,"characterOffsetEnd":2154,"pos":"NN","before":" ","after":" "},{"index":8,"word":"is","originalText":"is","characterOffsetBegin":2155,"characterOffsetEnd":2157,"pos":"VBZ","before":" ","after":" "},{"index":9,"word":"designed","originalText":"designed","characterOffsetBegin":2158,"characterOffsetEnd":2166,"pos":"VBN","before":" ","after":" "},{"index":10,"word":"to","originalText":"to","characterOffsetBegin":2167,"characterOffsetEnd":2169,"pos":"TO","before":" ","after":" "},{"index":11,"word":"work","originalText":"work","characterOffsetBegin":2170,"characterOffsetEnd":2174,"pos":"VB","before":" ","after":" "},{"index":12,"word":"primarily","originalText":"primarily","characterOffsetBegin":2175,"characterOffsetEnd":2184,"pos":"RB","before":" ","after":" "},{"index":13,"word":"with","originalText":"with","characterOffsetBegin":2185,"characterOffsetEnd":2189,"pos":"IN","before":" ","after":" "},{"index":14,"word":"analogsignals","originalText":"analogsignals","characterOffsetBegin":2190,"characterOffsetEnd":2203,"pos":"NNS","before":" ","after":""},{"index":15,"word":"?","originalText":"?","characterOffsetBegin":2203,"characterOffsetEnd":2204,"pos":".","before":"","after":"  "}]},{"index":12,"tokens":[{"index":1,"word":"The","originalText":"The","characterOffsetBegin":2206,"characterOffsetEnd":2209,"pos":"DT","before":"  ","after":" "},{"index":2,"word":"language","originalText":"language","characterOffsetBegin":2210,"characterOffsetEnd":2218,"pos":"NN","before":" ","after":" "},{"index":3,"word":"sort","originalText":"sort","characterOffsetBegin":2219,"characterOffsetEnd":2223,"pos":"NN","before":" ","after":" "},{"index":4,"word":"of","originalText":"of","characterOffsetBegin":2224,"characterOffsetEnd":2226,"pos":"IN","before":" ","after":" "},{"index":5,"word":"suggests","originalText":"suggests","characterOffsetBegin":2227,"characterOffsetEnd":2235,"pos":"VBZ","before":" ","after":" "},{"index":6,"word":"this","originalText":"this","characterOffsetBegin":2236,"characterOffsetEnd":2240,"pos":"DT","before":" ","after":""},{"index":7,"word":",","originalText":",","characterOffsetBegin":2240,"characterOffsetEnd":2241,"pos":",","before":"","after":" "},{"index":8,"word":"but","originalText":"but","characterOffsetBegin":2242,"characterOffsetEnd":2245,"pos":"CC","before":" ","after":" "},{"index":9,"word":"it","originalText":"it","characterOffsetBegin":2246,"characterOffsetEnd":2248,"pos":"PRP","before":" ","after":""},{"index":10,"word":"'s","originalText":"'s","characterOffsetBegin":2248,"characterOffsetEnd":2250,"pos":"VBZ","before":"","after":" "},{"index":11,"word":"hard","originalText":"hard","characterOffsetBegin":2251,"characterOffsetEnd":2255,"pos":"JJ","before":" ","after":" "},{"index":12,"word":"to","originalText":"to","characterOffsetBegin":2256,"characterOffsetEnd":2258,"pos":"TO","before":" ","after":" "},{"index":13,"word":"say.The","originalText":"say.The","characterOffsetBegin":2259,"characterOffsetEnd":2266,"pos":"NN","before":" ","after":" "},{"index":14,"word":"main","originalText":"main","characterOffsetBegin":2267,"characterOffsetEnd":2271,"pos":"JJ","before":" ","after":" "},{"index":15,"word":"thing","originalText":"thing","characterOffsetBegin":2272,"characterOffsetEnd":2277,"pos":"NN","before":" ","after":" "},{"index":16,"word":"I","originalText":"I","characterOffsetBegin":2278,"characterOffsetEnd":2279,"pos":"PRP","before":" ","after":" "},{"index":17,"word":"just","originalText":"just","characterOffsetBegin":2280,"characterOffsetEnd":2284,"pos":"RB","before":" ","after":" "},{"index":18,"word":"do","originalText":"do","characterOffsetBegin":2285,"characterOffsetEnd":2287,"pos":"VBP","before":" ","after":""},{"index":19,"word":"n't","originalText":"n't","characterOffsetBegin":2287,"characterOffsetEnd":2290,"pos":"RB","before":"","after":" "},{"index":20,"word":"get","originalText":"get","characterOffsetBegin":2291,"characterOffsetEnd":2294,"pos":"VB","before":" ","after":" "},{"index":21,"word":"is","originalText":"is","characterOffsetBegin":2295,"characterOffsetEnd":2297,"pos":"VBZ","before":" ","after":" "},{"index":22,"word":"whether","originalText":"whether","characterOffsetBegin":2298,"characterOffsetEnd":2305,"pos":"IN","before":" ","after":" "},{"index":23,"word":"this","originalText":"this","characterOffsetBegin":2306,"characterOffsetEnd":2310,"pos":"DT","before":" ","after":" "},{"index":24,"word":"chip","originalText":"chip","characterOffsetBegin":2311,"characterOffsetEnd":2315,"pos":"NN","before":" ","after":" "},{"index":25,"word":"implementssymmetric","originalText":"implementssymmetric","characterOffsetBegin":2316,"characterOffsetEnd":2335,"pos":"NN","before":" ","after":" "},{"index":26,"word":"or","originalText":"or","characterOffsetBegin":2336,"characterOffsetEnd":2338,"pos":"CC","before":" ","after":" "},{"index":27,"word":"asymmetric","originalText":"asymmetric","characterOffsetBegin":2339,"characterOffsetEnd":2349,"pos":"JJ","before":" ","after":" "},{"index":28,"word":"cryptographic","originalText":"cryptographic","characterOffsetBegin":2350,"characterOffsetEnd":2363,"pos":"JJ","before":" ","after":" "},{"index":29,"word":"techniques","originalText":"techniques","characterOffsetBegin":2364,"characterOffsetEnd":2374,"pos":"NNS","before":" ","after":""},{"index":30,"word":".","originalText":".","characterOffsetBegin":2374,"characterOffsetEnd":2375,"pos":".","before":"","after":"  "}]},{"index":13,"tokens":[{"index":1,"word":"Anybody","originalText":"Anybody","characterOffsetBegin":2377,"characterOffsetEnd":2384,"pos":"NN","before":"  ","after":" "},{"index":2,"word":"know?I","originalText":"know?I","characterOffsetBegin":2385,"characterOffsetEnd":2391,"pos":"NN","before":" ","after":""},{"index":3,"word":"'m","originalText":"'m","characterOffsetBegin":2391,"characterOffsetEnd":2393,"pos":"VBP","before":"","after":" "},{"index":4,"word":"guessing","originalText":"guessing","characterOffsetBegin":2394,"characterOffsetEnd":2402,"pos":"VBG","before":" ","after":" "},{"index":5,"word":"symmetric","originalText":"symmetric","characterOffsetBegin":2403,"characterOffsetEnd":2412,"pos":"JJ","before":" ","after":""},{"index":6,"word":",","originalText":",","characterOffsetBegin":2412,"characterOffsetEnd":2413,"pos":",","before":"","after":" "},{"index":7,"word":"but","originalText":"but","characterOffsetBegin":2414,"characterOffsetEnd":2417,"pos":"CC","before":" ","after":" "},{"index":8,"word":"they","originalText":"they","characterOffsetBegin":2418,"characterOffsetEnd":2422,"pos":"PRP","before":" ","after":" "},{"index":9,"word":"do","originalText":"do","characterOffsetBegin":2423,"characterOffsetEnd":2425,"pos":"VBP","before":" ","after":""},{"index":10,"word":"n't","originalText":"n't","characterOffsetBegin":2425,"characterOffsetEnd":2428,"pos":"RB","before":"","after":" "},{"index":11,"word":"get","originalText":"get","characterOffsetBegin":2429,"characterOffsetEnd":2432,"pos":"VB","before":" ","after":" "},{"index":12,"word":"very","originalText":"very","characterOffsetBegin":2433,"characterOffsetEnd":2437,"pos":"RB","before":" ","after":" "},{"index":13,"word":"clear","originalText":"clear","characterOffsetBegin":2438,"characterOffsetEnd":2443,"pos":"JJ","before":" ","after":" "},{"index":14,"word":"about","originalText":"about","characterOffsetBegin":2444,"characterOffsetEnd":2449,"pos":"IN","before":" ","after":" "},{"index":15,"word":"it","originalText":"it","characterOffsetBegin":2450,"characterOffsetEnd":2452,"pos":"PRP","before":" ","after":""},{"index":16,"word":".","originalText":".","characterOffsetBegin":2452,"characterOffsetEnd":2453,"pos":".","before":"","after":"  "}]},{"index":14,"tokens":[{"index":1,"word":"If","originalText":"If","characterOffsetBegin":2455,"characterOffsetEnd":2457,"pos":"IN","before":"  ","after":" "},{"index":2,"word":"itis","originalText":"itis","characterOffsetBegin":2458,"characterOffsetEnd":2462,"pos":"NN","before":" ","after":" "},{"index":3,"word":"symmetric","originalText":"symmetric","characterOffsetBegin":2463,"characterOffsetEnd":2472,"pos":"JJ","before":" ","after":""},{"index":4,"word":",","originalText":",","characterOffsetBegin":2472,"characterOffsetEnd":2473,"pos":",","before":"","after":" "},{"index":5,"word":"how","originalText":"how","characterOffsetBegin":2474,"characterOffsetEnd":2477,"pos":"WRB","before":" ","after":" "},{"index":6,"word":"is","originalText":"is","characterOffsetBegin":2478,"characterOffsetEnd":2480,"pos":"VBZ","before":" ","after":" "},{"index":7,"word":"it","originalText":"it","characterOffsetBegin":2481,"characterOffsetEnd":2483,"pos":"PRP","before":" ","after":" "},{"index":8,"word":"useful","originalText":"useful","characterOffsetBegin":2484,"characterOffsetEnd":2490,"pos":"JJ","before":" ","after":" "},{"index":9,"word":"for","originalText":"for","characterOffsetBegin":2491,"characterOffsetEnd":2494,"pos":"IN","before":" ","after":" "},{"index":10,"word":"anything","originalText":"anything","characterOffsetBegin":2495,"characterOffsetEnd":2503,"pos":"NN","before":" ","after":" "},{"index":11,"word":"other","originalText":"other","characterOffsetBegin":2504,"characterOffsetEnd":2509,"pos":"JJ","before":" ","after":" "},{"index":12,"word":"than","originalText":"than","characterOffsetBegin":2510,"characterOffsetEnd":2514,"pos":"IN","before":" ","after":" "},{"index":13,"word":"link-levelencryption","originalText":"link-levelencryption","characterOffsetBegin":2515,"characterOffsetEnd":2535,"pos":"JJ","before":" ","after":" "},{"index":14,"word":"with","originalText":"with","characterOffsetBegin":2536,"characterOffsetEnd":2540,"pos":"IN","before":" ","after":" "},{"index":15,"word":"an","originalText":"an","characterOffsetBegin":2541,"characterOffsetEnd":2543,"pos":"DT","before":" ","after":" "},{"index":16,"word":"identical","originalText":"identical","characterOffsetBegin":2544,"characterOffsetEnd":2553,"pos":"JJ","before":" ","after":" "},{"index":17,"word":"chip","originalText":"chip","characterOffsetBegin":2554,"characterOffsetEnd":2558,"pos":"NN","before":" ","after":" "},{"index":18,"word":"at","originalText":"at","characterOffsetBegin":2559,"characterOffsetEnd":2561,"pos":"IN","before":" ","after":" "},{"index":19,"word":"each","originalText":"each","characterOffsetBegin":2562,"characterOffsetEnd":2566,"pos":"DT","before":" ","after":" "},{"index":20,"word":"end","originalText":"end","characterOffsetBegin":2567,"characterOffsetEnd":2570,"pos":"NN","before":" ","after":""},{"index":21,"word":"?","originalText":"?","characterOffsetBegin":2570,"characterOffsetEnd":2571,"pos":".","before":"","after":"  "}]},{"index":15,"tokens":[{"index":1,"word":"How","originalText":"How","characterOffsetBegin":2573,"characterOffsetEnd":2576,"pos":"WRB","before":"  ","after":" "},{"index":2,"word":"can","originalText":"can","characterOffsetBegin":2577,"characterOffsetEnd":2580,"pos":"MD","before":" ","after":" "},{"index":3,"word":"you","originalText":"you","characterOffsetBegin":2581,"characterOffsetEnd":2584,"pos":"PRP","before":" ","after":" "},{"index":4,"word":"negotiatea","originalText":"negotiatea","characterOffsetBegin":2585,"characterOffsetEnd":2595,"pos":"VB","before":" ","after":" "},{"index":5,"word":"per-session","originalText":"per-session","characterOffsetBegin":2596,"characterOffsetEnd":2607,"pos":"NN","before":" ","after":" "},{"index":6,"word":"key","originalText":"key","characterOffsetBegin":2608,"characterOffsetEnd":2611,"pos":"NN","before":" ","after":" "},{"index":7,"word":"using","originalText":"using","characterOffsetBegin":2612,"characterOffsetEnd":2617,"pos":"VBG","before":" ","after":" "},{"index":8,"word":"symmetric","originalText":"symmetric","characterOffsetBegin":2618,"characterOffsetEnd":2627,"pos":"JJ","before":" ","after":" "},{"index":9,"word":"cryptography","originalText":"cryptography","characterOffsetBegin":2628,"characterOffsetEnd":2640,"pos":"NN","before":" ","after":" "},{"index":10,"word":"without","originalText":"without","characterOffsetBegin":2641,"characterOffsetEnd":2648,"pos":"IN","before":" ","after":" "},{"index":11,"word":"using","originalText":"using","characterOffsetBegin":2649,"characterOffsetEnd":2654,"pos":"VBG","before":" ","after":" "},{"index":12,"word":"a","originalText":"a","characterOffsetBegin":2655,"characterOffsetEnd":2656,"pos":"DT","before":" ","after":" "},{"index":13,"word":"trustedthird","originalText":"trustedthird","characterOffsetBegin":2657,"characterOffsetEnd":2669,"pos":"NN","before":" ","after":" "},{"index":14,"word":"party","originalText":"party","characterOffsetBegin":2670,"characterOffsetEnd":2675,"pos":"NN","before":" ","after":" "},{"index":15,"word":"who","originalText":"who","characterOffsetBegin":2676,"characterOffsetEnd":2679,"pos":"WP","before":" ","after":" "},{"index":16,"word":"knows","originalText":"knows","characterOffsetBegin":2680,"characterOffsetEnd":2685,"pos":"VBZ","before":" ","after":" "},{"index":17,"word":"your","originalText":"your","characterOffsetBegin":2686,"characterOffsetEnd":2690,"pos":"PRP$","before":" ","after":" "},{"index":18,"word":"key","originalText":"key","characterOffsetBegin":2691,"characterOffsetEnd":2694,"pos":"NN","before":" ","after":""},{"index":19,"word":"?","originalText":"?","characterOffsetBegin":2694,"characterOffsetEnd":2695,"pos":".","before":"","after":"  "}]},{"index":16,"tokens":[{"index":1,"word":"-LRB-","originalText":"(","characterOffsetBegin":2697,"characterOffsetEnd":2698,"pos":"-LRB-","before":"  ","after":""},{"index":2,"word":"Or","originalText":"Or","characterOffsetBegin":2698,"characterOffsetEnd":2700,"pos":"CC","before":"","after":" "},{"index":3,"word":"does","originalText":"does","characterOffsetBegin":2701,"characterOffsetEnd":2705,"pos":"VBZ","before":" ","after":" "},{"index":4,"word":"it","originalText":"it","characterOffsetBegin":2706,"characterOffsetEnd":2708,"pos":"PRP","before":" ","after":" "},{"index":5,"word":"even","originalText":"even","characterOffsetBegin":2709,"characterOffsetEnd":2713,"pos":"RB","before":" ","after":" "},{"index":6,"word":"use","originalText":"use","characterOffsetBegin":2714,"characterOffsetEnd":2717,"pos":"VBP","before":" ","after":" "},{"index":7,"word":"a","originalText":"a","characterOffsetBegin":2718,"characterOffsetEnd":2719,"pos":"DT","before":" ","after":" "},{"index":8,"word":"per-sessionkey","originalText":"per-sessionkey","characterOffsetBegin":2720,"characterOffsetEnd":2734,"pos":"NN","before":" ","after":""},{"index":9,"word":"?","originalText":"?","characterOffsetBegin":2734,"characterOffsetEnd":2735,"pos":".","before":"","after":""},{"index":10,"word":"-RRB-","originalText":")","characterOffsetBegin":2735,"characterOffsetEnd":2736,"pos":"-RRB-","before":"","after":""}]},{"index":17,"tokens":[{"index":1,"word":"If","originalText":"If","characterOffsetBegin":2736,"characterOffsetEnd":2738,"pos":"IN","before":"","after":" "},{"index":2,"word":"it","originalText":"it","characterOffsetBegin":2739,"characterOffsetEnd":2741,"pos":"PRP","before":" ","after":""},{"index":3,"word":"'s","originalText":"'s","characterOffsetBegin":2741,"characterOffsetEnd":2743,"pos":"VBZ","before":"","after":" "},{"index":4,"word":"asymmetric","originalText":"asymmetric","characterOffsetBegin":2744,"characterOffsetEnd":2754,"pos":"JJ","before":" ","after":""},{"index":5,"word":",","originalText":",","characterOffsetBegin":2754,"characterOffsetEnd":2755,"pos":",","before":"","after":" "},{"index":6,"word":"what","originalText":"what","characterOffsetBegin":2756,"characterOffsetEnd":2760,"pos":"WP","before":" ","after":" "},{"index":7,"word":"about","originalText":"about","characterOffsetBegin":2761,"characterOffsetEnd":2766,"pos":"IN","before":" ","after":" "},{"index":8,"word":"PKP","originalText":"PKP","characterOffsetBegin":2767,"characterOffsetEnd":2770,"pos":"NNP","before":" ","after":""},{"index":9,"word":"'s","originalText":"'s","characterOffsetBegin":2770,"characterOffsetEnd":2772,"pos":"POS","before":"","after":" "},{"index":10,"word":"patents","originalText":"patents","characterOffsetBegin":2773,"characterOffsetEnd":2780,"pos":"NNS","before":" ","after":""},{"index":11,"word":",","originalText":",","characterOffsetBegin":2780,"characterOffsetEnd":2781,"pos":",","before":"","after":" "},{"index":12,"word":"which","originalText":"which","characterOffsetBegin":2782,"characterOffsetEnd":2787,"pos":"WDT","before":" ","after":" "},{"index":13,"word":"they","originalText":"they","characterOffsetBegin":2788,"characterOffsetEnd":2792,"pos":"PRP","before":" ","after":" "},{"index":14,"word":"claim","originalText":"claim","characterOffsetBegin":2793,"characterOffsetEnd":2798,"pos":"VBP","before":" ","after":" "},{"index":15,"word":"coverall","originalText":"coverall","characterOffsetBegin":2799,"characterOffsetEnd":2807,"pos":"NN","before":" ","after":" "},{"index":16,"word":"methods","originalText":"methods","characterOffsetBegin":2808,"characterOffsetEnd":2815,"pos":"NNS","before":" ","after":" "},{"index":17,"word":"of","originalText":"of","characterOffsetBegin":2816,"characterOffsetEnd":2818,"pos":"IN","before":" ","after":" "},{"index":18,"word":"doing","originalText":"doing","characterOffsetBegin":2819,"characterOffsetEnd":2824,"pos":"VBG","before":" ","after":" "},{"index":19,"word":"asymmetric","originalText":"asymmetric","characterOffsetBegin":2825,"characterOffsetEnd":2835,"pos":"JJ","before":" ","after":" "},{"index":20,"word":"cryptography","originalText":"cryptography","characterOffsetBegin":2836,"characterOffsetEnd":2848,"pos":"NN","before":" ","after":""},{"index":21,"word":"?","originalText":"?","characterOffsetBegin":2848,"characterOffsetEnd":2849,"pos":".","before":"","after":"  "}]},{"index":18,"tokens":[{"index":1,"word":"Are","originalText":"Are","characterOffsetBegin":2851,"characterOffsetEnd":2854,"pos":"VBP","before":"  ","after":" "},{"index":2,"word":"they","originalText":"they","characterOffsetBegin":2855,"characterOffsetEnd":2859,"pos":"PRP","before":" ","after":" "},{"index":3,"word":"gettingroyalties","originalText":"gettingroyalties","characterOffsetBegin":2860,"characterOffsetEnd":2876,"pos":"NNS","before":" ","after":""},{"index":4,"word":",","originalText":",","characterOffsetBegin":2876,"characterOffsetEnd":2877,"pos":",","before":"","after":" "},{"index":5,"word":"or","originalText":"or","characterOffsetBegin":2878,"characterOffsetEnd":2880,"pos":"CC","before":" ","after":" "},{"index":6,"word":"is","originalText":"is","characterOffsetBegin":2881,"characterOffsetEnd":2883,"pos":"VBZ","before":" ","after":" "},{"index":7,"word":"hiding","originalText":"hiding","characterOffsetBegin":2884,"characterOffsetEnd":2890,"pos":"VBG","before":" ","after":" "},{"index":8,"word":"infringement","originalText":"infringement","characterOffsetBegin":2891,"characterOffsetEnd":2903,"pos":"NN","before":" ","after":" "},{"index":9,"word":"the","originalText":"the","characterOffsetBegin":2904,"characterOffsetEnd":2907,"pos":"DT","before":" ","after":" "},{"index":10,"word":"real","originalText":"real","characterOffsetBegin":2908,"characterOffsetEnd":2912,"pos":"JJ","before":" ","after":" "},{"index":11,"word":"reason","originalText":"reason","characterOffsetBegin":2913,"characterOffsetEnd":2919,"pos":"NN","before":" ","after":" "},{"index":12,"word":"for","originalText":"for","characterOffsetBegin":2920,"characterOffsetEnd":2923,"pos":"IN","before":" ","after":" "},{"index":13,"word":"keeping","originalText":"keeping","characterOffsetBegin":2924,"characterOffsetEnd":2931,"pos":"VBG","before":" ","after":" "},{"index":14,"word":"thealgorithm","originalText":"thealgorithm","characterOffsetBegin":2932,"characterOffsetEnd":2944,"pos":"NN","before":" ","after":" "},{"index":15,"word":"secret","originalText":"secret","characterOffsetBegin":2945,"characterOffsetEnd":2951,"pos":"NN","before":" ","after":""},{"index":16,"word":"?","originalText":"?","characterOffsetBegin":2951,"characterOffsetEnd":2952,"pos":".","before":"","after":" "}]},{"index":19,"tokens":[{"index":1,"word":":--RRB-","originalText":":-)","characterOffsetBegin":2953,"characterOffsetEnd":2956,"pos":"NN","before":" ","after":""},{"index":2,"word":"--","originalText":"--","characterOffsetBegin":2956,"characterOffsetEnd":2958,"pos":":","before":"","after":""},{"index":3,"word":"Marc","originalText":"Marc","characterOffsetBegin":2958,"characterOffsetEnd":2962,"pos":"NNP","before":"","after":" "},{"index":4,"word":"VanHeyningen","originalText":"VanHeyningen","characterOffsetBegin":2963,"characterOffsetEnd":2975,"pos":"NNP","before":" ","after":"   "},{"index":5,"word":"mvanheyn@cs.indiana.edu","originalText":"mvanheyn@cs.indiana.edu","characterOffsetBegin":2978,"characterOffsetEnd":3001,"pos":"NNP","before":"   ","after":"   "},{"index":6,"word":"MIME","originalText":"MIME","characterOffsetBegin":3004,"characterOffsetEnd":3008,"pos":"NNP","before":"   ","after":" "},{"index":7,"word":"&","originalText":"&","characterOffsetBegin":3009,"characterOffsetEnd":3010,"pos":"CC","before":" ","after":" "},{"index":8,"word":"RIPEM","originalText":"RIPEM","characterOffsetBegin":3011,"characterOffsetEnd":3016,"pos":"NNP","before":" ","after":" "},{"index":9,"word":"acceptedKirk","originalText":"acceptedKirk","characterOffsetBegin":3017,"characterOffsetEnd":3029,"pos":"NNP","before":" ","after":""},{"index":10,"word":":","originalText":":","characterOffsetBegin":3029,"characterOffsetEnd":3030,"pos":":","before":"","after":"  "},{"index":11,"word":"I","originalText":"I","characterOffsetBegin":3032,"characterOffsetEnd":3033,"pos":"PRP","before":"  ","after":" "},{"index":12,"word":"wo","originalText":"wo","characterOffsetBegin":3034,"characterOffsetEnd":3036,"pos":"MD","before":" ","after":""},{"index":13,"word":"n't","originalText":"n't","characterOffsetBegin":3036,"characterOffsetEnd":3039,"pos":"RB","before":"","after":" "},{"index":14,"word":"hurt","originalText":"hurt","characterOffsetBegin":3040,"characterOffsetEnd":3044,"pos":"VB","before":" ","after":" "},{"index":15,"word":"you.Alien","originalText":"you.Alien","characterOffsetBegin":3045,"characterOffsetEnd":3054,"pos":"NN","before":" ","after":""},{"index":16,"word":":","originalText":":","characterOffsetBegin":3054,"characterOffsetEnd":3055,"pos":":","before":"","after":" "},{"index":17,"word":"You","originalText":"You","characterOffsetBegin":3056,"characterOffsetEnd":3059,"pos":"PRP","before":" ","after":" "},{"index":18,"word":"hit","originalText":"hit","characterOffsetBegin":3060,"characterOffsetEnd":3063,"pos":"VBD","before":" ","after":" "},{"index":19,"word":"me!Kirk","originalText":"me!Kirk","characterOffsetBegin":3064,"characterOffsetEnd":3071,"pos":"NNP","before":" ","after":""},{"index":20,"word":":","originalText":":","characterOffsetBegin":3071,"characterOffsetEnd":3072,"pos":":","before":"","after":"  "},{"index":21,"word":"Well","originalText":"Well","characterOffsetBegin":3074,"characterOffsetEnd":3078,"pos":"UH","before":"  ","after":""},{"index":22,"word":",","originalText":",","characterOffsetBegin":3078,"characterOffsetEnd":3079,"pos":",","before":"","after":" "},{"index":23,"word":"I","originalText":"I","characterOffsetBegin":3080,"characterOffsetEnd":3081,"pos":"PRP","before":" ","after":" "},{"index":24,"word":"wo","originalText":"wo","characterOffsetBegin":3082,"characterOffsetEnd":3084,"pos":"MD","before":" ","after":""},{"index":25,"word":"n't","originalText":"n't","characterOffsetBegin":3084,"characterOffsetEnd":3087,"pos":"RB","before":"","after":" "},{"index":26,"word":"hit","originalText":"hit","characterOffsetBegin":3088,"characterOffsetEnd":3091,"pos":"VB","before":" ","after":" "},{"index":27,"word":"you","originalText":"you","characterOffsetBegin":3092,"characterOffsetEnd":3095,"pos":"PRP","before":" ","after":" "},{"index":28,"word":"again","originalText":"again","characterOffsetBegin":3096,"characterOffsetEnd":3101,"pos":"RB","before":" ","after":""},{"index":29,"word":".","originalText":".","characterOffsetBegin":3101,"characterOffsetEnd":3102,"pos":".","before":"","after":""}]}]}